robo_lib/__init__.py
robo_lib/components.py
robo_lib-1.0.6.dist-info/METADATA
robo_lib-1.0.6.dist-info/WHEEL
robo_lib-1.0.6.dist-info/licenses/LICENSE
robo_lib-1.0.6.dist-info/RECORD
