Metadata-Version: 2.4
Name: robo_lib
Version: 1.0.6
Summary: A package to create, configure, and train transformer models.
Project-URL: Homepage, https://github.com/hamburgerfish/robo_pack
Project-URL: Issues, https://github.com/hamburgerfish/robo_pack/issues
Author-email: Erik Papp <erik3papp@gmail.com>
License-File: LICENSE
Classifier: License :: OSI Approved :: MIT License
Classifier: Operating System :: OS Independent
Classifier: Programming Language :: Python :: 3
Requires-Python: >=3.8
Requires-Dist: numpy
Requires-Dist: tokenizers
Requires-Dist: torch
Requires-Dist: typing
